spidex/__init__.py
spidex/api.py
spidex_python_sdk2-0.1.10.dist-info/LICENSE.txt
spidex_python_sdk2-0.1.10.dist-info/METADATA
spidex_python_sdk2-0.1.10.dist-info/WHEEL
spidex_python_sdk2-0.1.10.dist-info/top_level.txt
spidex_python_sdk2-0.1.10.dist-info/zip-safe
spidex_python_sdk2-0.1.10.dist-info/RECORD
